graphcompass/__init__.py
graphcompass/__main__.py
graphcompass/py.typed
graphcompass/datasets/__init__.py
graphcompass/datasets/_dataset.py
graphcompass/datasets/_dataset.pyi
graphcompass/imports/wwl_package/__init__.py
graphcompass/imports/wwl_package/propagation_scheme.py
graphcompass/imports/wwl_package/wwl.py
graphcompass/pl/_WLkernel.py
graphcompass/pl/__init__.py
graphcompass/pl/_distance.py
graphcompass/pl/_filtration_curves.py
graphcompass/pl/utils.py
graphcompass/tl/_WLkernel.py
graphcompass/tl/__init__.py
graphcompass/tl/_distance.py
graphcompass/tl/_filtration_curves.py
graphcompass/tl/utils.py
graphcompass-0.2.5.dist-info/METADATA
graphcompass-0.2.5.dist-info/WHEEL
graphcompass-0.2.5.dist-info/licenses/LICENSE
graphcompass-0.2.5.dist-info/RECORD
