Metadata-Version: 2.4
Name: graphcompass
Version: 0.2.5
Summary: Spatial metrics for differential analyses of cell organization across conditions
Project-URL: Homepage, https://github.com/theislab/graphcompass
Project-URL: Bug Tracker, https://github.com/theislab/graphcompass/issues
Project-URL: Source Code, https://github.com/theislab/graphcompass
Author: Mayar Ali, Merel Kuijs
Maintainer-email: Mayar Ali <mayar.ali@helmholtz-munich.de>, Merel Kuijs <merelsentina.kuijs@helmholtz-munich.de>
License: MIT License
License-File: LICENSE
Keywords: bio-informatics,cell spatial organization,graph analytics,spatial data analysis,spatial omics,tissue architecture
Classifier: Development Status :: 4 - Beta
Classifier: Environment :: Console
Classifier: Framework :: Jupyter
Classifier: Intended Audience :: Science/Research
Classifier: License :: OSI Approved :: BSD License
Classifier: Natural Language :: English
Classifier: Operating System :: MacOS :: MacOS X
Classifier: Operating System :: POSIX :: Linux
Classifier: Programming Language :: Python :: 3
Classifier: Programming Language :: Python :: 3.9
Classifier: Programming Language :: Python :: 3.10
Classifier: Topic :: Scientific/Engineering :: Bio-Informatics
Classifier: Topic :: Scientific/Engineering :: Visualization
Classifier: Typing :: Typed
Requires-Python: <3.12,>=3.9
Requires-Dist: aiohttp>=3.8.1
Requires-Dist: anndata>=0.9
Requires-Dist: cycler>=0.11.0
Requires-Dist: cython>=3.0.2
Requires-Dist: dask-image>=0.5.0
Requires-Dist: dask[array]>=2021.02.0
Requires-Dist: docrep>=0.3.1
Requires-Dist: fsspec>=2021.11.0
Requires-Dist: igraph>=0.11.3
Requires-Dist: leidenalg>=0.8.2
Requires-Dist: matplotlib-scalebar>=0.8.0
Requires-Dist: matplotlib>=3.3
Requires-Dist: netlsd>=1.0.2
Requires-Dist: networkx>=2.8.6
Requires-Dist: numba>=0.56.4
Requires-Dist: numpy>=1.23.0
Requires-Dist: omnipath>=1.0.7
Requires-Dist: pandas>=2.1.0
Requires-Dist: pillow>=8.0.0
Requires-Dist: pot
Requires-Dist: scanpy>=1.9.3
Requires-Dist: scikit-image<=0.20,>=0.19
Requires-Dist: scikit-learn>=0.24.0
Requires-Dist: spatialdata
Requires-Dist: squidpy>=1.2.2
Requires-Dist: statannot>=0.2.3
Requires-Dist: statsmodels>=0.12.0
Requires-Dist: tifffile!=2022.4.22
Requires-Dist: tqdm>=4.50.2
Requires-Dist: validators>=0.18.2
Requires-Dist: xarray>=0.16.1
Requires-Dist: zarr>=2.6.1
